{
  "id": "discworld-modiphius",
  "title": "Terry Pratchett's Discworld - Official",
  "description": "Official implementation of \"Terry Pratchett's Discworld - Adventures in Ankh-Morpork\" by Modiphius",
  "version": "0.0.0",
  "license": "Apache License, Version 2.0",
  "compatibility": {
    "minimum": "13.338",
    "verified": "13"
  },
  "authors": [
    {
      "name": "MetaMorphic Digital Studio",
      "url": "https://metamorphic-digital.com/"
    },
    {
      "name": "Zhell",
      "discord": "zhell9201"
    },
    {
      "name": "Jalen Michals Levy",
      "discord": "jalensailin",
      "url": "https://github.com/jalensailin"
    }
  ],
  "esmodules": ["modules/discworld.js"],
  "styles": ["styles/main.css"],
  "languages": [
    {
      "lang": "en",
      "name": "English",
      "path": "lang/en.json"
    }
  ],
  "socket": false,
  "flags": {
    "hotReload": {
      "extensions": ["css", "hbs", "json"],
      "paths": ["styles", "templates", "lang"]
    }
  },
  "documentTypes": {
    "Actor": {
      "character": {
        "htmlFields": ["description"]
      }
    },
    "Item": {
      "trait": {
        "htmlFields": ["notes"]
      }
    }
  },
  "packs": [
    {
      "name": "discworld-quickstart",
      "label": "Quickstart",
      "system": "discworld-modiphius",
      "type": "JournalEntry",
      "path": "packs/discworld-quickstart"
    }
  ],
  "packFolders": [
    {
      "name": "Discworld",
      "sorting": "m",
      "color": "#7E4839",
      "packs": ["discworld-quickstart"]
    }
  ],
  "url": "",
  "manifest": "",
  "download": ""
}
